latexlib_kavesnin/__init__.py
latexlib_kavesnin/latex.py
latexlib_kavesnin-0.1.dist-info/METADATA
latexlib_kavesnin-0.1.dist-info/WHEEL
latexlib_kavesnin-0.1.dist-info/top_level.txt
latexlib_kavesnin-0.1.dist-info/RECORD
