Metadata-Version: 2.1
Name: latexlib-kavesnin
Version: 0.1
Summary: A library for generating LaTeX tables and images.
Home-page: https://github.com/kVesnin/latexlib_kavesnin
Author: Konstantin Vesnin
Author-email: kavesnin@edu.hse.ru
